License.txt
MANIFEST.in
README.rst
setup.py
PyStorage.egg-info/PKG-INFO
PyStorage.egg-info/SOURCES.txt
PyStorage.egg-info/dependency_links.txt
PyStorage.egg-info/top_level.txt
pystorage/VERSION
pystorage/__init__.py
pystorage/calc.py
pystorage/runsub.py
pystorage/EMC/__init__.py
pystorage/EMC/vmax.py
pystorage/EMC/vnx.py
pystorage/IBM/__init__.py
pystorage/IBM/ds8k.py