Metadata-Version: 1.1
Name: PyStorage
Version: 0.5.1
Summary: Python Storage Disk Toolkit (EMC VNX, EMC VMAX and IBM DS8K)
Home-page: https://github.com/kairoaraujo/PyStorage/
Author: Kairo Araujo
Author-email: kairo@kairo.eti.br
License: BSD
Keywords: Python Storage Disk EMC VMX VNX IBM DS800 DS8K Toolkit
Platform: Posix; MacOS X; Windows
Classifier: Development Status :: 3 - Alpha
Classifier: Intended Audience :: Developers
Classifier: License :: OSI Approved :: BSD License
Classifier: Operating System :: OS Independent
Classifier: Topic :: System :: Archiving
Classifier: Topic :: System :: Hardware
Classifier: Programming Language :: Python
Classifier: Programming Language :: Python :: 2
Classifier: Programming Language :: Python :: 2.6
Classifier: Programming Language :: Python :: 2.7
Classifier: Programming Language :: Python :: 3
Classifier: Programming Language :: Python :: 3.2
Classifier: Programming Language :: Python :: 3.3
Classifier: Programming Language :: Python :: 3.4
Classifier: Programming Language :: Python :: 3.5
